exporteer_evernote_osx/__init__.py
exporteer_evernote_osx/__main__.py
exporteer_evernote_osx/cli.py
exporteer_evernote_osx/enapp.py
exporteer_evernote_osx-0.0.4.dist-info/LICENSE
exporteer_evernote_osx-0.0.4.dist-info/METADATA
exporteer_evernote_osx-0.0.4.dist-info/WHEEL
exporteer_evernote_osx-0.0.4.dist-info/entry_points.txt
exporteer_evernote_osx-0.0.4.dist-info/top_level.txt
exporteer_evernote_osx-0.0.4.dist-info/RECORD
