Metadata-Version: 2.1
Name: exporteer-evernote-osx
Version: 0.0.4
Summary: Exports data from the Mac Evernote app.
Home-page: https://github.com/brokensandals/exporteer_evernote_osx
Author: Jacob Williams
Author-email: jacobaw@gmail.com
License: UNKNOWN
Platform: UNKNOWN
Classifier: Programming Language :: Python :: 3
Classifier: License :: OSI Approved :: MIT License
Classifier: Operating System :: MacOS :: MacOS X
Requires-Python: >=3.7
